tocsmith/__init__.py
tocsmith/cli.py
tocsmith/core.py
tocsmith/gui.py
tocsmith/tests/test_core.py
tocsmith-0.1.0.dist-info/METADATA
tocsmith-0.1.0.dist-info/WHEEL
tocsmith-0.1.0.dist-info/entry_points.txt
tocsmith-0.1.0.dist-info/top_level.txt
tocsmith-0.1.0.dist-info/RECORD
