Metadata-Version: 2.4
Name: tocsmith
Version: 0.1.0
Summary: Create PDF bookmarks automatically using heuristics, with CLI and async tkinter GUI
Author-email: Wesley Yang <yxnian@outlook.com>
Project-URL: Homepage, https://github.com/wesleyel/pdf-bookmark
Project-URL: Source, https://github.com/wesleyel/pdf-bookmark
Requires-Python: >=3.9
Requires-Dist: pypdf>=4.2.0
Requires-Dist: tomli>=2.0.1; python_version < "3.11"
Provides-Extra: dev
Requires-Dist: pytest>=8.2; extra == "dev"
Requires-Dist: pytest-cov>=5.0; extra == "dev"
Requires-Dist: ruff>=0.5.0; extra == "dev"
Requires-Dist: mypy>=1.10.0; extra == "dev"
